df_lib_syren/__init__.py
df_lib_syren-0.0.3.dist-info/LICENCE.txt
df_lib_syren-0.0.3.dist-info/METADATA
df_lib_syren-0.0.3.dist-info/WHEEL
df_lib_syren-0.0.3.dist-info/top_level.txt
df_lib_syren-0.0.3.dist-info/RECORD
