Metadata-Version: 2.1
Name: df-lib-syren
Version: 0.0.3
Summary: COMPARISON OF DATAFRAMES
Home-page: UNKNOWN
Author: seshkalyan
Author-email: dseshkalyan@gmail.com
License: SYREN CLOUD TECHNOLOGIES
Platform: UNKNOWN
License-File: LICENCE.txt
